free_grok/__init__.py
free_grok/conf.py
free_grok/grok.py
free_grok-0.1.0.dist-info/WHEEL
free_grok-0.1.0.dist-info/METADATA
free_grok-0.1.0.dist-info/RECORD
