Metadata-Version: 2.3
Name: free-grok
Version: 0.1.0
Summary: Free Grok API
Author: dummyjenil
Author-email: dummyjenil <dummyjenil@gmail.com>
Requires-Dist: curl-cffi
Requires-Dist: coincurve
Requires-Dist: beautifulsoup4
Requires-Dist: platformdirs
